README.md
setup.cfg
setup.py
dsnd_probability_cwc/Binomialdistribution.py
dsnd_probability_cwc/Gaussiandistribution.py
dsnd_probability_cwc/Generaldistribution.py
dsnd_probability_cwc/__init__.py
dsnd_probability_cwc.egg-info/PKG-INFO
dsnd_probability_cwc.egg-info/SOURCES.txt
dsnd_probability_cwc.egg-info/dependency_links.txt
dsnd_probability_cwc.egg-info/not-zip-safe
dsnd_probability_cwc.egg-info/top_level.txt