Metadata-Version: 1.0
Name: dsnd-probability-cwc
Version: 0.2
Summary: Gaussian abd Binomial Distribution
Home-page: UNKNOWN
Author: Chin-Wen Chang
Author-email: UNKNOWN
License: UNKNOWN
Platform: UNKNOWN
